<?xml version="1.0" encoding="UTF-8"?><Publication xmlns:dc="http://purl.org/dc/elements/1.1/" xmlns:xsi="http://www.w3.org/2001/XMLSchema-instance" ID="F2544" type="Fiche Question-réponse" xsi:noNamespaceSchemaLocation="../Schemas/3.0/Publication.xsd">
<dc:title>Peut-on encore bénéficier du minimum vieillesse ?</dc:title>
<dc:creator>Direction de l'information légale et administrative</dc:creator>
<dc:subject>Social - Santé</dc:subject>
<dc:description>Non, l'allocation de solidarité aux personnes âgées (Aspa) remplace le minimum vieillesse depuis 2006</dc:description>
<dc:publisher>Direction de l'information légale et administrative</dc:publisher>
<dc:contributor>Direction de l'information légale et administrative (Premier ministre)</dc:contributor>
<dc:date>modified 2016-04-01</dc:date>
<dc:type>Question-réponse</dc:type>
<dc:format>text/xml</dc:format>
<dc:identifier>F2544</dc:identifier>
<dc:source>http://www.legislation.cnav.fr/Pages/texte.aspx?Nom=circulaire_cnav_2014_028_09042014</dc:source>
<dc:language>Fr</dc:language>
<dc:relation>isPartOf N392</dc:relation>
<dc:coverage>France entière</dc:coverage>
<dc:rights>https://www.service-public.fr/a-propos/mentions-legales</dc:rights>
<SurTitre>Question-réponse</SurTitre>
<Audience>Particuliers</Audience>
<Canal>www.service-public.fr</Canal>
<FilDAriane>
<Niveau ID="Particuliers">Accueil particuliers</Niveau>
<Niveau ID="N19811">Social - Santé</Niveau>
<Niveau ID="N392">Allocations et aides aux personnes âgées</Niveau>
<Niveau ID="F2544" type="Fiche Question-réponse">Peut-on encore bénéficier du minimum vieillesse ?</Niveau>
</FilDAriane>
<Theme ID="N19811">
<Titre>Social - Santé</Titre>
</Theme>
<SousThemePere ID="N20274">Aides sociales</SousThemePere><DossierPere ID="N392">
<Titre>Allocations et aides aux personnes âgées</Titre>
<Fiche ID="F10009">Allocation personnalisée d'autonomie (Apa)</Fiche>
<Fiche ID="F16871">Allocation de solidarité aux personnes âgées (Aspa)</Fiche>
<Fiche ID="F16940">Allocation supplémentaire d'invalidité (Asi)</Fiche>
<Fiche ID="F2572">Allocation simple</Fiche>
<Fiche ID="F245">Aide-ménagère à domicile</Fiche>
<Fiche ID="F248">Prise en charge des repas</Fiche>
</DossierPere>

<Texte><Paragraphe>Non, le minimum vieillesse était un dispositif qui garantissait à une personne âgée disposant de faibles revenus, un niveau minimum de ressources. Depuis le 1er janvier 2006, l'<LienInterne LienPublication="F16871" type="Fiche d'information" audience="Particuliers">Allocation de solidarité aux personnes âgées (ASPA)</LienInterne> remplace les multiples prestations du minimum vieillesse. </Paragraphe>
<Paragraphe>Seules les personnes qui bénéficiaient des allocations du minimum vieillesse avant 2006, ou qui ont commencé à en bénéficier en 2006 (avant que les textes relatifs à l'Aspa soient applicables), peuvent continuer à les percevoir si elles n'ont pas demandé à bénéficier de l'Aspa. Le basculement n'est pas automatique.</Paragraphe>
<Paragraphe>Le  minimum vieillesse est un dispositif à 2 niveaux :</Paragraphe>
<Liste type="puce">
<Item>
<Paragraphe> le premier niveau garantit à la personne âgée un revenu au minimum  égal au montant de l'allocation aux vieux travailleurs salariés (AVTS). Lorsque les ressources du retraité  sont inférieures à ce montant,  une majoration de pension lui est accordée. Si la personne âgée ne peut prétendre à aucune retraite, l'allocation spéciale vieillesse lui est versée.</Paragraphe>
</Item>
<Item>
<Paragraphe>le 2<Exposant>e</Exposant> niveau est constitué par l'allocation supplémentaire qui permet d'atteindre le niveau du minimum vieillesse.</Paragraphe>
</Item>
</Liste>
<Paragraphe>Le montant du minimum vieillesse est fixé à (<Valeur>801 €</Valeur> par mois pour une personne seule et <Valeur>1 243 €</Valeur> par mois pour un couple).</Paragraphe>
<Paragraphe>Il faut remplir les conditions suivantes :</Paragraphe>
<Liste type="puce">
<Item>
<Paragraphe>Être Français ou étranger en situation régulière,</Paragraphe>
</Item>
<Item>
<Paragraphe>Résider en France,</Paragraphe>
</Item>
<Item>
<Paragraphe>Avoir commencé à  bénéficier du minimum vieillesse avant 2006,</Paragraphe>
</Item>
</Liste>
<Liste type="puce">
<Item>
<Paragraphe>Disposer de ressources inférieures à certains plafonds.</Paragraphe>
</Item>
</Liste>
<Paragraphe>Les plafonds de ressources diffèrent selon qu'il s'agit d'une personne seule ou d'un couple.</Paragraphe>
<Tableau>
<Titre>Plafond de ressources pour continuer à percevoir le minimum vieillesse </Titre>
<Colonne largeur="28" type="header"/>
<Colonne largeur="28" type="normal"/>
<Colonne largeur="28" type="normal"/>
<Rangée type="header">
<Cellule>
<Paragraphe>Plafond de ressources</Paragraphe>
</Cellule>
<Cellule>
<Paragraphe>Pour une personne seule</Paragraphe>
</Cellule>
<Cellule>
<Paragraphe>Pour un couple</Paragraphe>
</Cellule>
</Rangée>
<Rangée type="normal">
<Cellule>
<Paragraphe>Plafond annuel</Paragraphe>
</Cellule>
<Cellule>
<Paragraphe>
<Valeur>9 609,6 €</Valeur>
</Paragraphe>
</Cellule>
<Cellule>
<Paragraphe>
<Valeur>14 918,9 €</Valeur>
</Paragraphe>
</Cellule>
</Rangée>
<Rangée type="normal">
<Cellule>
<Paragraphe>Plafond mensuel</Paragraphe>
</Cellule>
<Cellule>
<Paragraphe>
<Valeur>801 €</Valeur>
</Paragraphe>
</Cellule>
<Cellule>
<Paragraphe>
<Valeur>1 243 €</Valeur>
</Paragraphe>
</Cellule>
</Rangée>
</Tableau>
<Tableau>
<Titre>Montants mensuels des prestations constituant le minimum vieillesse</Titre>
<Colonne largeur="25" type="normal"/>
<Colonne largeur="29" type="normal"/>
<Colonne largeur="33" type="normal"/>
<Rangée type="header">
<Cellule fusionVerticale="2">
<Paragraphe>Prestations</Paragraphe>
</Cellule>
<Cellule fusionHorizontale="2">
<Paragraphe>Montants mensuels</Paragraphe>
</Cellule>
</Rangée>
<Rangée type="header">
<Cellule>
<Paragraphe>Pour une personne seule</Paragraphe>
</Cellule>
<Cellule>
<Paragraphe>Pour un couple</Paragraphe>
</Cellule>
</Rangée>
<Rangée type="normal">
<Cellule>
<Paragraphe>Allocation aux vieux travailleurs salariés (AVTS)</Paragraphe>
</Cellule>
<Cellule>
<Paragraphe>
<Valeur>281,94 €</Valeur> </Paragraphe>
</Cellule>
<Cellule>
<Paragraphe>
<Valeur>281,94 €</Valeur> </Paragraphe>
</Cellule>
</Rangée>
<Rangée type="normal">
<Cellule>
<Paragraphe>Allocation aux vieux travailleurs non salariés (AVTNS)</Paragraphe>
</Cellule>
<Cellule>
<Paragraphe>
<Valeur>281,94 €</Valeur> </Paragraphe>
</Cellule>
<Cellule>
<Paragraphe>
<Valeur>281,94 €</Valeur> </Paragraphe>
</Cellule>
</Rangée>
<Rangée type="normal">
<Cellule>
<Paragraphe>Allocation aux mères de famille (AMF)</Paragraphe>
</Cellule>
<Cellule>
<Paragraphe>
<Valeur>281,94 €</Valeur> </Paragraphe>
</Cellule>
<Cellule>
<Paragraphe>
<Valeur>281,94 €</Valeur> </Paragraphe>
</Cellule>
</Rangée>
<Rangée type="normal">
<Cellule>
<Paragraphe>Secours viager</Paragraphe>
</Cellule>
<Cellule>
<Paragraphe>
<Valeur>281,94 €</Valeur>
</Paragraphe>
</Cellule>
<Cellule>
<Paragraphe>
<Valeur>281,94 €</Valeur> </Paragraphe>
</Cellule>
</Rangée>
<Rangée type="normal">
<Cellule>
<Paragraphe>Allocation spéciale vieillesse</Paragraphe>
</Cellule>
<Cellule>
<Paragraphe>
<Valeur>281,94 €</Valeur>
</Paragraphe>
</Cellule>
<Cellule>
<Paragraphe>
<Valeur>281,94 €</Valeur> </Paragraphe>
</Cellule>
</Rangée>
<Rangée type="normal">
<Cellule>
<Paragraphe>Allocation viagère</Paragraphe>
</Cellule>
<Cellule>
<Paragraphe>
<Valeur>281,94 €</Valeur>
</Paragraphe>
</Cellule>
<Cellule>
<Paragraphe>
<Valeur>281,94 €</Valeur> </Paragraphe>
</Cellule>
</Rangée>
<Rangée type="normal">
<Cellule>
<Paragraphe>Allocation de vieillesse agricole</Paragraphe>
</Cellule>
<Cellule>
<Paragraphe>
<Valeur>281,94 €</Valeur>
</Paragraphe>
</Cellule>
<Cellule>
<Paragraphe>
<Valeur>281,94 €</Valeur> </Paragraphe>
</Cellule>
</Rangée>
<Rangée type="normal">
<Cellule>
<Paragraphe>Allocation supplémentaire (montants maximum)</Paragraphe>
</Cellule>
<Cellule>
<Paragraphe>
<Valeur>518,86 €</Valeur> </Paragraphe>
</Cellule>
<Cellule>
<Paragraphe>
<Valeur>679,35 €</Valeur> </Paragraphe>
</Cellule>
</Rangée>
</Tableau>
<Paragraphe>Les sommes versées au titre de l’allocation supplémentaire sont récupérées sur la succession si le montant de celle-ci (actif net successoral) est supérieur à <Valeur>39 000 €</Valeur>.</Paragraphe>

</Texte><OuSAdresser ID="R198" type="Centre de contact">
<Titre>Assurance retraite - 39 60</Titre>
<Source ID="R30670">Caisse nationale d'assurance vieillesse (Cnav)</Source><Texte>
						
								<Paragraphe>Pour  s'informer, poser une question sur votre dossier, accéder à des informations personnelles (suivi du dossier, derniers paiements, etc.).</Paragraphe>
							
						<Chapitre>
<Titre>
<Paragraphe>Par téléphone</Paragraphe>
</Titre>
								<Paragraphe>
			<MiseEnEvidence>39 60</MiseEnEvidence>
       (ou 
			09 71 10 39 60 depuis un mobile, une box ou l'étranger)</Paragraphe>
								<Paragraphe>Numéro violet ou majoré : coût d'un appel vers un numéro fixe + service payant, depuis un téléphone fixe ou mobile</Paragraphe>
								<Paragraphe>Pour connaître le tarif, écoutez le message en début d'appel</Paragraphe>
								<Paragraphe>Du lundi au vendredi de 8h à 17h</Paragraphe>
							</Chapitre>
					</Texte>
</OuSAdresser>
<OuSAdresser ID="R39" type="Local personnalisé sur SP">
<Titre>Mutualité sociale agricole (MSA)</Titre>
<Complement>Pour tout renseignement si vous êtes béneficiaire du minimum vieillesse</Complement>
<PivotLocal>msa</PivotLocal>
<RessourceWeb URL="http://www.msa.fr/lfr/contacter-une-msa"/>
<Source ID="R30660">Caisse centrale de la mutualité sociale agricole (MSA)</Source>
</OuSAdresser>
<Reference type="Texte de référence" URL="http://www.legislation.cnav.fr/Pages/texte.aspx?Nom=circulaire_cnav_2014_028_09042014" ID="R20364">
<Titre>Circulaire Cnav 2014-28 du 9 avril 2014 sur la revalorisation à compter du 1er avril 2014</Titre>
<Source ID="R30670">Caisse nationale d'assurance vieillesse (Cnav)</Source>
<Complement>Revalorisation annuelle en avril</Complement>
</Reference>
</Publication>
