<?xml version="1.0" encoding="UTF-8"?><Publication xmlns:dc="http://purl.org/dc/elements/1.1/" xmlns:xsi="http://www.w3.org/2001/XMLSchema-instance" ID="F33790" type="Fiche Question-réponse" xsi:noNamespaceSchemaLocation="../Schemas/3.0/Publication.xsd">
<dc:title>Qu'est ce que la force majeure en droit du travail ?</dc:title>
<dc:creator>Direction de l'information légale et administrative</dc:creator>
<dc:subject>Travail</dc:subject>
<dc:description>C'est un événement à la fois imprévisible, irrésistible et extérieur aux personnes concernées. Par exemple, une catastrophe naturelle, une grève de</dc:description>
<dc:publisher>Direction de l'information légale et administrative</dc:publisher>
<dc:contributor>Direction de l'information légale et administrative (Premier ministre)</dc:contributor>
<dc:date>modified 2016-07-06</dc:date>
<dc:type>Question-réponse</dc:type>
<dc:format>text/xml</dc:format>
<dc:identifier>F33790</dc:identifier>
<dc:source>http://www.legifrance.gouv.fr/affichCode.do?idSectionTA=LEGISCTA000006195624&amp;cidTexte=LEGITEXT000006072050, http://www.legifrance.gouv.fr/affichCode.do?idSectionTA=LEGISCTA000006189458&amp;cidTexte=LEGITEXT000006072050, http://www.legifrance.gouv.fr/affichCode.do?idSectionTA=LEGISCTA000006198549&amp;cidTexte=LEGITEXT000006072050</dc:source>
<dc:language>Fr</dc:language>
<dc:relation>isPartOf N492</dc:relation>
<dc:coverage>France entière</dc:coverage>
<dc:rights>https://www.service-public.fr/a-propos/mentions-legales</dc:rights>
<SurTitre>Question-réponse</SurTitre>
<Audience>Particuliers</Audience>
<Canal>www.service-public.fr</Canal>
<FilDAriane>
<Niveau ID="Particuliers">Accueil particuliers</Niveau>
<Niveau ID="N19806">Travail</Niveau>
<Niveau ID="N492">Conditions de travail dans le secteur privé</Niveau>
<Niveau ID="F33790" type="Fiche Question-réponse">Qu'est ce que la force majeure en droit du travail ?</Niveau>
</FilDAriane>
<Theme ID="N19806">
<Titre>Travail</Titre>
</Theme>
<SousThemePere ID="N19965">Santé, sécurité et conditions de travail</SousThemePere><DossierPere ID="N492">
<Titre>Conditions de travail dans le secteur privé</Titre><SousDossier ID="N492-1">
<Titre>Hygiène, sécurité et conditions de travail</Titre>
<Fiche ID="F2210">Obligations de l'employeur</Fiche>
<Fiche ID="F2344">Jeunes dans l'entreprise</Fiche>
<Fiche ID="F58">Travailleur à domicile</Fiche>
<Fiche ID="F2211">Médecine du travail</Fiche>
<Fiche ID="F15504">Compte de prévention pénibilité</Fiche>
<Fiche ID="F13851">Télétravail</Fiche>
</SousDossier>
<SousDossier ID="N492-2">
<Titre>Travail de nuit</Titre>
<Fiche ID="F2212">Principes généraux</Fiche>
<Fiche ID="F1688">Jeunes de moins de 18 ans</Fiche>
<Fiche ID="F2691">Protection de la salariée enceinte</Fiche>
</SousDossier>
<SousDossier ID="N492-3">
<Titre>Conditions de travail : informations diverses</Titre>
<Fiche ID="F31854">Évaluation du salarié</Fiche>
<Fiche ID="F1905">Règlement intérieur d'une entreprise</Fiche>
<Fiche ID="F78">Convention collective</Fiche>
</SousDossier>
</DossierPere>

<Texte><Paragraphe>C'est un événement à la fois :</Paragraphe>
<Liste type="puce">
<Item>
<Paragraphe> imprévisible,</Paragraphe>
</Item>
<Item>
<Paragraphe>irrésistible, </Paragraphe>
</Item>
<Item>
<Paragraphe>et extérieur aux personnes concernées, c'est à dire dont ni l'employeur ni le salarié ne sont responsables. </Paragraphe>
</Item>
</Liste>
<Paragraphe>La situation de force majeure libère, temporairement ou définitivement, l'employeur ou le salarié des obligations liées au contrat de travail.</Paragraphe>
<Paragraphe>Exemples de cas de force majeure :</Paragraphe>
<Liste type="puce">
<Item>
<Paragraphe>une catastrophe naturelle entraînant une cessation totale de l'activité de l'entreprise,</Paragraphe>
</Item>
<Item>
<Paragraphe>un sinistre (incendie des locaux),</Paragraphe>
</Item>
<Item>
<Paragraphe>une grève de grande ampleur qui empêche le salarié de se rendre à son travail</Paragraphe>
</Item>
</Liste>
<Paragraphe>Les situations suivantes ne sont pas des cas de force majeure :</Paragraphe>
<Liste type="puce">
<Item>
<Paragraphe>le licenciement économique et la liquidation judiciaire,</Paragraphe>
</Item>
<Item>
<Paragraphe>le décès de l'employeur,</Paragraphe>
</Item>
<Item>
<Paragraphe>l'incarcération du salarié,</Paragraphe>
</Item>
<Item>
<Paragraphe>la maladie ou l'inaptitude physique du salarié.</Paragraphe>
</Item>
</Liste>
<Paragraphe>En cas de litige, ce sont les tribunaux qui décident si l'événement relève de la force majeure.</Paragraphe>

</Texte><VoirAussi important="non">
<Fiche ID="F24412" audience="Particuliers">
<Titre>Rupture du contrat de travail pour cas de force majeure</Titre>
<Theme ID="N19806">
<Titre>Travail</Titre>
</Theme>
</Fiche>
</VoirAussi>

<Reference type="Texte de référence" URL="http://www.legifrance.gouv.fr/affichCode.do?idSectionTA=LEGISCTA000006195624&amp;cidTexte=LEGITEXT000006072050" ID="R40584">
<Titre>Code du travail : articles L1234-12 à L1234-13</Titre>
</Reference>
<Reference type="Texte de référence" URL="http://www.legifrance.gouv.fr/affichCode.do?idSectionTA=LEGISCTA000006189458&amp;cidTexte=LEGITEXT000006072050" ID="R36301">
<Titre>Code du travail : articles L1243-1 à L1243-4</Titre>
</Reference>
<Reference type="Texte de référence" URL="http://www.legifrance.gouv.fr/affichCode.do?idSectionTA=LEGISCTA000006198549&amp;cidTexte=LEGITEXT000006072050" ID="R20165">
<Titre>Code du travail : articles L1251-26 à L1251-28</Titre>
</Reference>
</Publication>
