<?xml version="1.0" encoding="UTF-8"?><Publication xmlns:dc="http://purl.org/dc/elements/1.1/" xmlns:xsi="http://www.w3.org/2001/XMLSchema-instance" ID="F744" type="Fiche d'information" xsi:noNamespaceSchemaLocation="../Schemas/3.0/Publication.xsd">
<dc:title>Allocation veuvage</dc:title>
<dc:creator>Direction de l'information légale et administrative</dc:creator>
<dc:subject>Famille</dc:subject>
<dc:description>Au décès de votre époux(se), vous pouvez bénéficier d'une allocation de veuvage sous certaines conditions liées notamment à votre âge et à vos ressources.</dc:description>
<dc:publisher>Direction de l'information légale et administrative</dc:publisher>
<dc:contributor>Direction de l'information légale et administrative (Premier ministre)</dc:contributor>
<dc:date>modified 2015-10-13</dc:date>
<dc:type>Fiche pratique</dc:type>
<dc:format>text/xml</dc:format>
<dc:identifier>F744</dc:identifier>
<dc:source>http://www.legifrance.gouv.fr/affichCode.do?idSectionTA=LEGISCTA000023034913&amp;cidTexte=LEGITEXT000006073189&amp;dateTexte=vig, http://www.legifrance.gouv.fr/affichCode.do?idSectionTA=LEGISCTA000023413992&amp;cidTexte=LEGITEXT000006073189, http://www.legifrance.gouv.fr/affichCode.do?idSectionTA=LEGISCTA000006189793&amp;cidTexte=LEGITEXT000006072050&amp;dateTexte=vig, http://circulaires.legifrance.gouv.fr/pdf/2015/10/cir_40077.pdf</dc:source>
<dc:language>Fr</dc:language>
<dc:relation>isPartOf N31163</dc:relation>
<dc:coverage>France entière</dc:coverage>
<dc:rights>https://www.service-public.fr/a-propos/mentions-legales</dc:rights>
<SurTitre>Fiche pratique</SurTitre>
<Audience>Particuliers</Audience>
<Canal>www.service-public.fr</Canal>
<FilDAriane>
<Niveau ID="Particuliers">Accueil particuliers</Niveau>
<Niveau ID="N19805">Famille</Niveau>
<Niveau ID="N31163">Rentes et capitaux versés en cas de décès</Niveau>
<Niveau ID="F744" type="Fiche d'information">Allocation veuvage</Niveau>
</FilDAriane>
<Theme ID="N19805">
<Titre>Famille</Titre>
</Theme>
<SousThemePere ID="N31161">Décès</SousThemePere><DossierPere ID="N31163">
<Titre>Rentes et capitaux versés en cas de décès</Titre><SousDossier ID="N31163-1">
<Titre>Capital décès</Titre>
<Fiche ID="F3005">Capital décès versé pour le décès d'un salarié du secteur privé</Fiche>
<Fiche ID="F1544">Capital décès versé pour le décès d'un fonctionnaire</Fiche>
</SousDossier>
<SousDossier ID="N31163-2">
<Titre>Allocations et indemnités</Titre>
<Fiche ID="F744">Allocation veuvage</Fiche>
<Fiche ID="F14868">Accident du travail : indemnisation des ayants droit</Fiche>
<Fiche ID="F32172">Maladie professionnelle : indemnisation des ayants droit</Fiche>
</SousDossier>
</DossierPere>

<SousDossierPere>Allocations et indemnités</SousDossierPere>
<Introduction>
<Texte><Paragraphe>Au décès de votre époux(se), vous pouvez bénéficier d'une allocation de veuvage sous certaines conditions liées notamment à votre âge et à vos ressources.</Paragraphe>
</Texte>
</Introduction>
<Texte><Chapitre>
<Titre>
<Paragraphe>Conditions liées au conjoint décédé</Paragraphe>
</Titre><Paragraphe>Votre époux(se) doit avoir cotisé à l'assurance vieillesse au moins 3 mois, continus ou non, durant l'année précédant le décès.</Paragraphe>

</Chapitre>
<Chapitre>
<Titre>
<Paragraphe>Conditions liées au veuf (ou veuve)</Paragraphe>
</Titre><SousChapitre>
<Titre>
<Paragraphe>Âge</Paragraphe>
</Titre>
<Paragraphe>Vous devez avoir moins de 55 ans.</Paragraphe>
<ASavoir>
<Titre>À savoir</Titre><Paragraphe>si vous avez 55 ans ou plus, vous pouvez demander une pension de réversion.</Paragraphe>
</ASavoir>
</SousChapitre>
<SousChapitre>
<Titre>
<Paragraphe>Résidence</Paragraphe>
</Titre><Paragraphe>Vous devez résider en France.</Paragraphe>
<Paragraphe>Toutefois, des exceptions existent. Vous pouvez vous renseigner  auprès de <LienInterne LienPublication="R198" type="Centre de contact" audience="Particuliers">l'Assurance retraite</LienInterne> ou de la Mutualité sociale agricole ou  de <LienInterne LienPublication="F2504" type="Fiche Question-réponse" audience="Particuliers">la caisse de retraite concernée</LienInterne>.</Paragraphe>

</SousChapitre>
<SousChapitre>
<Titre>
<Paragraphe>Situation familiale</Paragraphe>
</Titre><Paragraphe>Vous devez être :</Paragraphe>
<Liste type="puce">
<Item>
<Paragraphe>Veuf ou veuve </Paragraphe>
</Item>
<Item>
<Paragraphe>Et ne pas vivre en couple (remariage, vie maritale, Pacs)</Paragraphe>
</Item>
</Liste>

</SousChapitre>
<SousChapitre>
<Titre>
<Paragraphe>Ressources</Paragraphe>
</Titre><Paragraphe>Vos ressources des 3 mois civils avant votre demande ne doivent pas dépasser <Valeur>2 260,27 €</Valeur>, soit <Valeur>753,42 €</Valeur> par mois.</Paragraphe>

</SousChapitre>
</Chapitre>
<Chapitre>
<Titre>
<Paragraphe>Quand faire la demande ?</Paragraphe>
</Titre><Paragraphe>Dans les 2 ans du 1<Exposant>er</Exposant> jour du mois du décès.</Paragraphe>

</Chapitre>
<Chapitre>
<Titre>
<Paragraphe>Comment faire la demande ?</Paragraphe>
</Titre><Paragraphe>Le dossier est lié au régime dont vous dépendez.</Paragraphe>
<BlocCas affichage="onglet">
<Cas>
<Titre>
<Paragraphe>Régime général de la Sécurité sociale </Paragraphe>
</Titre><ServiceEnLigne ID="R1339" URL="https://www.lassuranceretraite.fr/portail-info/files/live/sites/pub-bootstrap/files/Guides%20et%20formulaires/demande-allocation-veuvage.pdf" numerocerfa="12098*04 + notice n°51443#02" type="Formulaire">
<Titre>Demande d'allocation de veuvage auprès de la Cnav</Titre>
<Source ID="R30662">Ministère en charge de la santé</Source>
</ServiceEnLigne>


</Cas>
<Cas>
<Titre>
<Paragraphe>Mutualité sociale agricole (MSA) </Paragraphe>
</Titre><ServiceEnLigne ID="R32890" URL="https://www.formulaires.modernisation.gouv.fr/gf/cerfa_14954.do" numerocerfa="14954*01" type="Formulaire">
<Titre>Demande d'allocation veuvage auprès de la MSA</Titre>
<Source ID="R30660">Caisse centrale de la mutualité sociale agricole (MSA)</Source>
<Introduction>
<Texte><Paragraphe>Contient une notice explicative qui indique comment compléter le formulaire et les justificatifs à joindre.</Paragraphe>
</Texte>
</Introduction><NoticeLiee ID="R32891" URL="https://www.formulaires.modernisation.gouv.fr/gf/getAnnexe.do?cerfaAnnexe=14954*01&amp;cerfaFormulaire=14954*01" format="application/pdf" poids="106.9 KB">Notice d'aide au remplissage du formulaire</NoticeLiee>
</ServiceEnLigne>


</Cas>
</BlocCas>

<Paragraphe>Vous devez adresser votre demande, en priorité, à la <LienInterne LienPublication="F2504" type="Fiche Question-réponse" audience="Particuliers">caisse du dernier lieu de travail de votre conjoint décédé</LienInterne>.</Paragraphe>
<Paragraphe>Toutefois, vous pouvez aussi  envoyer votre demande à une autre caisse (par exemple, celle de votre domicile).</Paragraphe>

</Chapitre>
<Chapitre>
<Titre>
<Paragraphe>Versement de l'allocation</Paragraphe>
</Titre><SousChapitre>
<Titre>
<Paragraphe>Point de départ</Paragraphe>
</Titre><Paragraphe>Le point de départ de votre allocation dépend de la date à laquelle vous en faites la demande :</Paragraphe>
<Liste type="puce">
<Item>
<Paragraphe>Au  1<Exposant>er</Exposant> jour du mois au cours duquel s'est produit le décès si vous faites votre demande dans les  12 mois suivant le décès</Paragraphe>
</Item>
</Liste>
<Liste type="puce">
<Item>
<Paragraphe>Au 1<Exposant>er</Exposant> jour du mois de votre demande si vous faites votre demande au-delà des 12 mois suivant le décès</Paragraphe>
</Item>
</Liste>

</SousChapitre>
<SousChapitre>
<Titre>
<Paragraphe>Périodicité</Paragraphe>
</Titre>
<Paragraphe>L'allocation est versée tous les mois.</Paragraphe>

</SousChapitre>
<SousChapitre>
<Titre>
<Paragraphe>Montant</Paragraphe>
</Titre><Paragraphe>Le montant net de l'allocation veuvage est de <Valeur>602,73 €</Valeur> par mois.</Paragraphe>
<Paragraphe>Le montant peut être réduit en fonction de vos ressources.</Paragraphe>

</SousChapitre>
<SousChapitre>
<Titre>
<Paragraphe>Cumul d'activité</Paragraphe>
</Titre>
<Paragraphe>En cas de formation rémunérée ou de reprise d'une activité professionnelle,  vous pouvez cumuler les revenus perçus avec l'allocation de veuvage  dans une certaine limite et pendant un certain temps.</Paragraphe>
<Paragraphe>Vous pouvez vous renseigner  auprès de <LienInterne LienPublication="R198" type="Centre de contact" audience="Particuliers">l'Assurance retraite</LienInterne> ou de <LienInterne LienPublication="F2504" type="Fiche Question-réponse" audience="Particuliers">la caisse de retraite concernée.</LienInterne>
</Paragraphe>

</SousChapitre>
<SousChapitre>
<Titre>
<Paragraphe>Durée</Paragraphe>
</Titre><Paragraphe>Vous percevez l'allocation veuvage :</Paragraphe>
<Liste type="puce">
<Item>
<Paragraphe>Tant que vous remplissez les conditions</Paragraphe>
</Item>
<Item>
<Paragraphe>Au maximum pendant 2 ans (ou jusqu'à vos 55 ans si vous aviez 50 ans à la date du décès de votre conjoint)</Paragraphe>
</Item>
</Liste>
<ANoter>
<Titre>À noter</Titre>
<Paragraphe>vous devez informer votre caisse de tout changement de situation (ressources, situation familiale, etc.).</Paragraphe>
</ANoter>
</SousChapitre>
</Chapitre>
</Texte><VoirAussi important="non">
<Dossier ID="N31163" audience="Particuliers">
<Titre>Rentes et capitaux versés en cas de décès</Titre>
<Theme ID="N19805">
<Titre>Famille</Titre>
</Theme>
</Dossier>
<Dossier ID="N378" audience="Particuliers">
<Titre>Pension de réversion</Titre>
<Theme ID="N19805">
<Titre>Famille</Titre>
</Theme>
</Dossier>
</VoirAussi>
<OuSAdresser ID="R198" type="Centre de contact">
<Titre>Assurance retraite - 39 60</Titre>
<Complement>Pour s'informer</Complement>
<Source ID="R30670">Caisse nationale d'assurance vieillesse (Cnav)</Source><Texte>
						
								<Paragraphe>Pour  s'informer, poser une question sur votre dossier, accéder à des informations personnelles (suivi du dossier, derniers paiements, etc.).</Paragraphe>
							
						<Chapitre>
<Titre>
<Paragraphe>Par téléphone</Paragraphe>
</Titre>
								<Paragraphe>
			<MiseEnEvidence>39 60</MiseEnEvidence>
       (ou 
			09 71 10 39 60 depuis un mobile, une box ou l'étranger)</Paragraphe>
								<Paragraphe>Numéro violet ou majoré : coût d'un appel vers un numéro fixe + service payant, depuis un téléphone fixe ou mobile</Paragraphe>
								<Paragraphe>Pour connaître le tarif, écoutez le message en début d'appel</Paragraphe>
								<Paragraphe>Du lundi au vendredi de 8h à 17h</Paragraphe>
							</Chapitre>
					</Texte>
</OuSAdresser>
<Reference type="Texte de référence" URL="http://www.legifrance.gouv.fr/affichCode.do?idSectionTA=LEGISCTA000023034913&amp;cidTexte=LEGITEXT000006073189&amp;dateTexte=vig" ID="R31867">
<Titre>Code de la sécurité sociale : articles L356-1 à L356-5</Titre>
<Complement>Définition et conditions</Complement>
</Reference>
<Reference type="Texte de référence" URL="http://www.legifrance.gouv.fr/affichCode.do?idSectionTA=LEGISCTA000023413992&amp;cidTexte=LEGITEXT000006073189" ID="R31868">
<Titre>Code de la sécurité sociale : articles D356-1 à D356-13</Titre>
<Complement>Conditions liées au conjoint décédé (article D356-1), conditions liées au bénéficiaire (articles D356-2 à D356-4), durée de versement (article D356-5), date d'effet (article D356-6), montant mensuel (article D356-7), demande (articles D356-8 à D356-9)</Complement>
</Reference>
<Reference type="Texte de référence" URL="http://www.legifrance.gouv.fr/affichCode.do?idSectionTA=LEGISCTA000006189793&amp;cidTexte=LEGITEXT000006072050&amp;dateTexte=vig" ID="R31869">
<Titre>Code du travail : articles L5141-3 à L5141-4</Titre>
<Complement>Cumul d'activité (article L5141-4)</Complement>
</Reference>
<Reference type="Texte de référence" URL="http://circulaires.legifrance.gouv.fr/pdf/2015/10/cir_40077.pdf" ID="R42005">
<Titre>Circulaire n°DSS/SD3A/2015/299 du 1er octobre 2015 relative à la revalorisation des pensions de vieillesse au 1er octobre 2015</Titre>
</Reference>
<ServiceEnLigne ID="R1339" URL="https://www.lassuranceretraite.fr/portail-info/files/live/sites/pub-bootstrap/files/Guides%20et%20formulaires/demande-allocation-veuvage.pdf" numerocerfa="12098*04 + notice n°51443#02" type="Formulaire">
<Titre>Demande d'allocation de veuvage auprès de la Cnav</Titre>
<Source ID="R30662">Ministère en charge de la santé</Source>
</ServiceEnLigne>
<ServiceEnLigne ID="R32890" URL="https://www.formulaires.modernisation.gouv.fr/gf/cerfa_14954.do" numerocerfa="14954*01" type="Formulaire">
<Titre>Demande d'allocation veuvage auprès de la MSA</Titre>
<Source ID="R30660">Caisse centrale de la mutualité sociale agricole (MSA)</Source><NoticeLiee ID="R32891" URL="https://www.formulaires.modernisation.gouv.fr/gf/getAnnexe.do?cerfaAnnexe=14954*01&amp;cerfaFormulaire=14954*01" format="application/pdf" poids="106.9 KB">Notice d'aide au remplissage du formulaire</NoticeLiee>
</ServiceEnLigne>
<ServiceEnLigne ID="R32895" URL="https://www.formulaires.modernisation.gouv.fr/gf/cerfa_14955.do" type="Formulaire">
<Titre>Déclaration familiale et de ressources (MSA)</Titre>
<Source ID="R30660">Caisse centrale de la mutualité sociale agricole (MSA)</Source>
</ServiceEnLigne>
<PourEnSavoirPlus type="Information pratique" ID="R19594" URL="https://www.lassuranceretraite.fr/portail-info/home/salaries/mes-droits-selon-de-mon-parcours/en-cas-de-deces.html" audience="Particuliers">
<Titre>Vos droits en cas de décès de l'époux</Titre>
<Source ID="R30670">Caisse nationale d'assurance vieillesse (Cnav)</Source>
</PourEnSavoirPlus>
<PourEnSavoirPlus type="Information pratique" ID="R41813" URL="https://www.lassuranceretraite.fr/portail-info/accueil" commentaireLien="site d'information concernant la retraite de la sécurité sociale" audience="Particuliers">
<Titre>Site de la retraite de la Sécurité sociale</Titre>
<Source ID="R30670">Caisse nationale d'assurance vieillesse (Cnav)</Source>
</PourEnSavoirPlus>

</Publication>
