<?xml version="1.0" encoding="UTF-8"?><Publication xmlns:dc="http://purl.org/dc/elements/1.1/" xmlns:xsi="http://www.w3.org/2001/XMLSchema-instance" ID="F31596" type="Fiche d'information" xsi:noNamespaceSchemaLocation="../Schemas/3.0/Publication.xsd">
<dc:title>Taux de TVA pour les services à la personne</dc:title>
<dc:creator>Direction de l'information légale et administrative</dc:creator>
<dc:subject>Fiscalité</dc:subject>
<dc:description>Les services à la personne sont constitués de prestations s'adressant aux particuliers, effectuées par un organisme de services à la personne ou un entrepreneur individuel (y compris un auto-entrepreneur s'il en remplit les conditions). Ces activités sont soumises à des taux de TVA différents en fonction de leur nature.</dc:description>
<dc:publisher>Direction de l'information légale et administrative</dc:publisher>
<dc:contributor>Direction de l'information légale et administrative (Premier ministre)</dc:contributor>
<dc:date>modified 2015-12-16</dc:date>
<dc:type>Fiche pratique</dc:type>
<dc:format>text/xml</dc:format>
<dc:identifier>F31596</dc:identifier>
<dc:source>http://www.legifrance.gouv.fr/affichCode.do?idSectionTA=LEGISCTA000006191654&amp;cidTexte=LEGITEXT000006069577, http://legifrance.gouv.fr/affichCode.do?idSectionTA=LEGISCTA000027570469&amp;cidTexte=LEGITEXT000006069574, http://bofip.impots.gouv.fr/bofip/780-PGP</dc:source>
<dc:language>Fr</dc:language>
<dc:relation>isPartOf N13445</dc:relation>
<dc:coverage>France entière</dc:coverage>
<dc:rights>https://www.service-public.fr/a-propos/mentions-legales</dc:rights>
<SurTitre>Fiche pratique</SurTitre>
<Audience>Professionnels</Audience>
<Canal>www.service-public.fr</Canal>
<Cible>Tout professionnel</Cible>
<FilDAriane>
<Niveau ID="Professionnels">Accueil professionnels</Niveau>
<Niveau ID="N24265">Fiscalité</Niveau>
<Niveau ID="N13445">Taxe sur la valeur ajoutée (TVA)</Niveau>
<Niveau ID="F31596" type="Fiche d'information">Taux de TVA pour les services à la personne</Niveau>
</FilDAriane>
<Theme ID="N24265">
<Titre>Fiscalité</Titre>
</Theme>
<SousThemePere ID="N10736">Impôts liés au chiffre d'affaires</SousThemePere><DossierPere ID="N13445">
<Titre>Taxe sur la valeur ajoutée (TVA)</Titre><SousDossier ID="N13445-1">
<Titre>Taux applicables</Titre>
<Fiche ID="F23567">Application des différents taux de TVA</Fiche>
<Fiche ID="F22399">Restauration et débits de boisson</Fiche>
<Fiche ID="F23568">Travaux de rénovation d'un logement</Fiche>
<Fiche ID="F20558">Vente en détaxe aux touristes</Fiche>
<Fiche ID="F20781">Secteur culturel (œuvres d'art et spectacles vivants)</Fiche>
<Fiche ID="F32113">Droits d'auteur</Fiche>
<Fiche ID="F31596">Services à la personne</Fiche>
</SousDossier>
<SousDossier ID="N13445-2">
<Titre>Déclaration de la TVA</Titre>
<Fiche ID="F23566">Déclaration et paiement de la TVA</Fiche>
<Fiche ID="F21746">Franchise en base de TVA</Fiche>
<Fiche ID="F23569">Déduction de la TVA sur les achats professionnels</Fiche>
<Fiche ID="F24026">Contributions et taxes assimilées à la TVA</Fiche>
<Fiche ID="F31983">Autoliquidation de la TVA en cas de sous-traitance dans le BTP</Fiche>
</SousDossier>
<SousDossier ID="N13445-3">
<Titre>Commerce international et TVA</Titre>
<Fiche ID="F33340">TVA applicable aux échanges européens</Fiche>
<Fiche ID="F23570">Numéro de TVA intracommunautaire</Fiche>
<Fiche ID="F31673">Remboursement de la TVA intracommunautaire</Fiche>
<Fiche ID="F33167">Autoliquidation de la TVA due à l'importation</Fiche>
</SousDossier>
</DossierPere>

<SousDossierPere>Taux applicables</SousDossierPere>
<Introduction>
<Texte><Paragraphe>Les services à la personne sont constitués de prestations s'adressant aux particuliers, effectuées par un organisme de services à la personne ou un entrepreneur individuel (y compris un auto-entrepreneur s'il en remplit les conditions). Ces activités sont soumises à des taux de TVA différents en fonction de leur nature.</Paragraphe>
</Texte>
</Introduction>
<Texte><Chapitre>
<Titre>
<Paragraphe>Taux de TVA</Paragraphe>
</Titre><Paragraphe>Le taux réduit de 5,5 % s'applique uniquement aux activités nécessitant un agrément préfectoral préalable, liées aux gestes essentiels de la vie quotidienne des personnes handicapées et âgées dépendantes, fournies par des organismes agréés.</Paragraphe>
<Paragraphe>Sont exclues  des taux réduits les prestations de services rendues par des organismes opérant en tant que simples mandataires, y compris les frais de gestion qu'ils facturent aux employeurs.</Paragraphe>
<Tableau>
<Titre>Taux de TVA des services à la personne</Titre>
<Colonne largeur="33" type="normal"/>
<Colonne largeur="50" type="normal"/>
<Colonne largeur="50" type="normal"/>
<Rangée type="header">
<Cellule>
<Paragraphe>Taux à 20 %</Paragraphe>
</Cellule>
<Cellule>
<Paragraphe>Taux à 10 %</Paragraphe>
</Cellule>
<Cellule>
<Paragraphe>Taux à 5,5 %</Paragraphe>
</Cellule>
</Rangée>
<Rangée type="normal">
<Cellule>
<Paragraphe>Petits travaux de jardinage</Paragraphe>
</Cellule>
<Cellule>
<Paragraphe>Entretien de la maison, travaux ménagers et petit bricolage ("homme toutes mains")</Paragraphe>
</Cellule>
<Cellule>
<Paragraphe>Assistance aux personnes âgées à partir de 60 ans ou dépendantes à domicile (sauf actes de soins et actes médicaux)</Paragraphe>
</Cellule>
</Rangée>
<Rangée type="normal">
<Cellule>
<Paragraphe>Cours à domicile (hors soutien scolaire)</Paragraphe>
</Cellule>
<Cellule>
<Paragraphe>Préparation et livraison de repas à domicile (livraison de courses à domicile)</Paragraphe>
</Cellule>
<Cellule>
<Paragraphe>Garde-malade</Paragraphe>
</Cellule>
</Rangée>
<Rangée type="normal">
<Cellule>
<Paragraphe>Assistance informatique et internet à domicile</Paragraphe>
</Cellule>
<Cellule>
<Paragraphe>Collecte et livraison à domicile de linge repassé</Paragraphe>
</Cellule>
<Cellule>
<Paragraphe>Aide à la mobilité, accompagnement, transport de personnes ayant des difficultés de déplacement - Conduite du véhicule personnel des personnes dépendantes</Paragraphe>
</Cellule>
</Rangée>
<Rangée type="normal">
<Cellule>
<Paragraphe>Activités d'organisation des services à la personne (par le mandataire qui met en relation un client et un prestataire de services à la personne)</Paragraphe>
</Cellule>
<Cellule>
<Paragraphe>Garde d'enfants et soutien scolaire à domicile - Accompagnement d'enfants dans leurs déplacements hors du domicile (promenades, transport, actes de la vie courante)</Paragraphe>
</Cellule>
<Cellule>
<Paragraphe>Assistance aux personnes handicapées (y compris les activités d'interprète en langue des signes, de technicien de l'écrit et de codeur en langage parlé complété)</Paragraphe>
</Cellule>
</Rangée>
<Rangée type="normal">
<Cellule>
<Paragraphe>Maintenance, l'entretien et la vigilance temporaires, à domicile, de la résidence principale et secondaire</Paragraphe>
</Cellule>
<Cellule>
<Paragraphe>Soins et promenades d'animaux de compagnie (sauf soins vétérinaires et toilettage), pour les personnes dépendantes</Paragraphe>
</Cellule>
<Cellule>
<Paragraphe>Fourniture de logement et de nourriture dans les maisons de retraite et les établissements accueillant des personnes handicapées</Paragraphe>
</Cellule>
</Rangée>
<Rangée type="normal">
<Cellule/>
<Cellule>
<Paragraphe>Soins d'esthétique à domicile pour les personnes dépendantes</Paragraphe>
</Cellule>
<Cellule>
<Paragraphe>Prestations exclusivement liées à la dépendance des personnes âgées ou handicapées, qui sont dans l'incapacité d'accomplir les gestes essentiels de la vie quotidienne</Paragraphe>
</Cellule>
</Rangée>
<Rangée type="normal">
<Cellule/>
<Cellule>
<Paragraphe>Assistance administrative à domicile</Paragraphe>
</Cellule>
<Cellule/>
</Rangée>
</Tableau>
<Attention>
<Titre>Attention</Titre><Paragraphe>pour bénéficier des avantages fiscaux, les activités de services à la personne doivent être exercées à titre exclusif par le prestataire, sauf pour les structures qui bénéficient d'une dérogation à la condition d'activité exclusive.</Paragraphe>
</Attention>
</Chapitre>
<Chapitre>
<Titre>
<Paragraphe>Conditions pour l'application du taux réduit</Paragraphe>
</Titre><Paragraphe>S'agissant des prestations effectuées à domicile, les services doivent être effectués au domicile des personnes physiques situé en France.</Paragraphe>
<Paragraphe>Ils peuvent être également effectués dans l'environnement immédiat du domicile, s'ils contribuent au maintien à domicile des personnes en constituant une alternative à l'hospitalisation ou au long séjour en établissement spécialisé.</Paragraphe>
<Paragraphe>Certaines activités ne sont éligibles au taux réduit de 5,5 % qu'à la condition d'être fournies à des personnes dépendantes, définies comme étant momentanément ou durablement atteintes de pathologies chroniques invalidantes ou présentant une affection les empêchant d'accomplir les actes ordinaires de la vie quotidienne.</Paragraphe>

</Chapitre>
</Texte><Reference type="Texte de référence" URL="http://www.legifrance.gouv.fr/affichCode.do?idSectionTA=LEGISCTA000006191654&amp;cidTexte=LEGITEXT000006069577" ID="R22410">
<Titre>Code général des impôts : articles 278-0 bis à 279 bis</Titre>
</Reference>
<Reference type="Texte de référence" URL="http://legifrance.gouv.fr/affichCode.do?idSectionTA=LEGISCTA000027570469&amp;cidTexte=LEGITEXT000006069574" ID="R32613">
<Titre>Code général des impôts, annexe 3 : article 86</Titre>
<Complement>Liste des activités bénéficiant du taux réduit de TVA</Complement>
</Reference>
<Reference type="Texte de référence" URL="http://bofip.impots.gouv.fr/bofip/780-PGP" ID="R36071">
<Titre>Bofip-Impôts n°BOI-TVA-LIQ-30-20-80 sur les taux réduits des services d'aide à la personne</Titre>
</Reference>
</Publication>
